logload/__init__.py
logload/logload.py
logload/words.txt
logload-0.1.1.dist-info/DESCRIPTION.rst
logload-0.1.1.dist-info/METADATA
logload-0.1.1.dist-info/RECORD
logload-0.1.1.dist-info/WHEEL
logload-0.1.1.dist-info/entry_points.txt
logload-0.1.1.dist-info/metadata.json
logload-0.1.1.dist-info/top_level.txt
