Metadata-Version: 2.0
Name: logload
Version: 0.1.1
Summary: A syslog network load generator.
Home-page: https://github.com/ofosos/logload/
Author: Mark Meyer
Author-email: mark@ofosos.org
License: GPLv3
Keywords: network syslog testing load
Platform: UNKNOWN
Classifier: Development Status :: 3 - Alpha
Classifier: Programming Language :: Python :: 3
Classifier: Programming Language :: Python :: 3.5
Classifier: License :: OSI Approved :: GNU General Public License v3 or later (GPLv3+)
Classifier: Topic :: System :: Logging
Classifier: Topic :: Software Development :: Testing :: Traffic Generation
Requires-Dist: funcparserlib
